pcap_analysis/__init__.py
pcap_analysis/_dpkt_cnv.py
pcap_analysis/_packet_analyzer.py
pcap_analysis/_analyzers/__init__.py
pcap_analysis/_analyzers/arp.py
pcap_analysis/_analyzers/bootp.py
pcap_analysis/_analyzers/dhcp.py
pcap_analysis/_analyzers/icmp.py
pcap_analysis-0.1.1.dist-info/LICENSE
pcap_analysis-0.1.1.dist-info/METADATA
pcap_analysis-0.1.1.dist-info/WHEEL
pcap_analysis-0.1.1.dist-info/top_level.txt
pcap_analysis-0.1.1.dist-info/RECORD
